README.md
setup.cfg
setup.py
bin/__init__.py
bin/stanchion.py
examples/__init__.py
examples/commit/__init__.py
examples/commit/adversaries_commit.py
examples/commit/campaigns_commit.py
examples/commit/custom_indicators_commit.py
examples/commit/documents_commit.py
examples/commit/emails_commit.py
examples/commit/incidents_commit.py
examples/commit/indicators_commit.py
examples/commit/manual_commit.py
examples/commit/signatures_commit.py
examples/commit/tasks_commit.py
examples/commit/threats_commit.py
examples/commit/vicitms_commit.py
examples/retrieve/__init__.py
examples/retrieve/adversaries_retrieve.py
examples/retrieve/bulk_indicators.py
examples/retrieve/campaigns_retrieve.py
examples/retrieve/custom_indicator_retrieve.py
examples/retrieve/documents_retrieve.py
examples/retrieve/emails_retrieve.py
examples/retrieve/groups_retrieve.py
examples/retrieve/incidents_retrieve.py
examples/retrieve/indicators_retrieve.py
examples/retrieve/manual_retrieve.py
examples/retrieve/owners_metric_retrieve.py
examples/retrieve/owners_retrieve.py
examples/retrieve/signatures_retrieve.py
examples/retrieve/tasks_retrieve.py
examples/retrieve/threats_retrieve.py
examples/retrieve/victims_retrieve.py
threatconnect/ApiProperties.py
threatconnect/AttributeObject.py
threatconnect/BatchJobFilterMethods.py
threatconnect/BatchJobObject.py
threatconnect/DnsResolutionObject.py
threatconnect/ErrorCodes.py
threatconnect/FileOccurrenceObject.py
threatconnect/FilterObject.py
threatconnect/GroupFilterMethods.py
threatconnect/GroupObject.py
threatconnect/IndicatorFilterMethods.py
threatconnect/IndicatorObject.py
threatconnect/IndicatorObjectAdvanced.py
threatconnect/IndicatorObjectParser.py
threatconnect/IndicatorObjectTyped.py
threatconnect/ObservationObject.py
threatconnect/OwnerFilterMethods.py
threatconnect/OwnerMembersObject.py
threatconnect/OwnerMetricsObject.py
threatconnect/OwnerObject.py
threatconnect/PostFilterObject.py
threatconnect/Report.py
threatconnect/ReportEntry.py
threatconnect.egg-info/PKG-INFO
threatconnect.egg-info/SOURCES.txt
threatconnect.egg-info/dependency_links.txt
threatconnect.egg-info/entry_points.txt
threatconnect.egg-info/requires.txt
threatconnect.egg-info/top_level.txt
