Metadata-Version: 1.1
Name: threatconnect
Version: 2.4.21
Summary: Python SDK for ThreatConnect API
Home-page: https://github.com/ThreatConnect-Inc/threatconnect-python
Author: ThreatConnect (support@threatconnect.com)
Author-email: support@threatconnect.com
License: Apache License, Version 2
Download-URL: https://github.com/ThreatConnect-Inc/threatconnect-python/archive/2.4.21.tar.gz
Platform: UNKNOWN
Classifier: Development Status :: 5 - Production/Stable
Classifier: Intended Audience :: Developers
Classifier: Topic :: Software Development :: Libraries :: Python Modules
Classifier: License :: OSI Approved :: Apache Software License
